{
  "Player": {
    "FirstName": "Mikel",
    "LastName": "Rico Moreno",
    "CommonName": "Mikel Rico",
    "Height": "178",
    "DateOfBirth": {
      "Year": "1984",
      "Month": "11",
      "Day": "4"
    },
    "PreferredFoot": "Right",
    "ClubId": "110832",
    "LeagueId": "53",
    "NationId": "45",
    "Rating": "70",
    "Attribute1": "68",
    "Attribute2": "58",
    "Attribute3": "63",
    "Attribute4": "60",
    "Attribute5": "73",
    "Attribute6": "67",
    "Rare": "0",
    "ItemType": "PlayerM"
  }
}