{
  "Player": {
    "FirstName": "Moisés",
    "LastName": "Muñoz",
    "CommonName": null,
    "Height": "183",
    "DateOfBirth": {
      "Year": "1980",
      "Month": "2",
      "Day": "1"
    },
    "PreferredFoot": "Right",
    "ClubId": "101116",
    "LeagueId": "341",
    "NationId": "83",
    "Rating": "70",
    "Attribute1": "70",
    "Attribute2": "72",
    "Attribute3": "62",
    "Attribute4": "73",
    "Attribute5": "46",
    "Attribute6": "69",
    "Rare": "0",
    "ItemType": "PlayerGk"
  }
}