{
  "Player": {
    "FirstName": "Angelo",
    "LastName": "Rea",
    "CommonName": null,
    "Height": "185",
    "DateOfBirth": {
      "Year": "1982",
      "Month": "6",
      "Day": "16"
    },
    "PreferredFoot": "Right",
    "ClubId": "111974",
    "LeagueId": "32",
    "NationId": "27",
    "Rating": "63",
    "Attribute1": "63",
    "Attribute2": "31",
    "Attribute3": "47",
    "Attribute4": "47",
    "Attribute5": "66",
    "Attribute6": "67",
    "Rare": "0",
    "ItemType": "PlayerD"
  }
}