{
  "Player": {
    "FirstName": "Martin",
    "LastName": "Stranzl",
    "CommonName": null,
    "Height": "190",
    "DateOfBirth": {
      "Year": "1980",
      "Month": "6",
      "Day": "16"
    },
    "PreferredFoot": "Right",
    "ClubId": "23",
    "LeagueId": "19",
    "NationId": "4",
    "Rating": "74",
    "Attribute1": "60",
    "Attribute2": "54",
    "Attribute3": "66",
    "Attribute4": "57",
    "Attribute5": "76",
    "Attribute6": "70",
    "Rare": "1",
    "ItemType": "PlayerD"
  }
}