{
  "Player": {
    "FirstName": "Michele",
    "LastName": "Canini",
    "CommonName": null,
    "Height": "187",
    "DateOfBirth": {
      "Year": "1985",
      "Month": "6",
      "Day": "5"
    },
    "PreferredFoot": "Right",
    "ClubId": "1842",
    "LeagueId": "31",
    "NationId": "27",
    "Rating": "76",
    "Attribute1": "66",
    "Attribute2": "45",
    "Attribute3": "66",
    "Attribute4": "47",
    "Attribute5": "78",
    "Attribute6": "79",
    "Rare": "0",
    "ItemType": "PlayerD"
  }
}