{
  "Player": {
    "FirstName": "Michele",
    "LastName": "Paolucci",
    "CommonName": null,
    "Height": "182",
    "DateOfBirth": {
      "Year": "1986",
      "Month": "2",
      "Day": "6"
    },
    "PreferredFoot": "Right",
    "ClubId": "1847",
    "LeagueId": "32",
    "NationId": "27",
    "Rating": "68",
    "Attribute1": "73",
    "Attribute2": "69",
    "Attribute3": "54",
    "Attribute4": "67",
    "Attribute5": "54",
    "Attribute6": "65",
    "Rare": "0",
    "ItemType": "PlayerA"
  }
}