{
  "Player": {
    "FirstName": "Anderson Miguel",
    "LastName": "da Silva",
    "CommonName": "Nenê",
    "Height": "183",
    "DateOfBirth": {
      "Year": "1983",
      "Month": "7",
      "Day": "28"
    },
    "PreferredFoot": "Right",
    "ClubId": "1842",
    "LeagueId": "31",
    "NationId": "54",
    "Rating": "73",
    "Attribute1": "65",
    "Attribute2": "73",
    "Attribute3": "57",
    "Attribute4": "69",
    "Attribute5": "54",
    "Attribute6": "79",
    "Rare": "1",
    "ItemType": "PlayerA"
  }
}