{
  "Player": {
    "FirstName": "Ivan",
    "LastName": "Perišić",
    "CommonName": null,
    "Height": "187",
    "DateOfBirth": {
      "Year": "1989",
      "Month": "2",
      "Day": "2"
    },
    "PreferredFoot": "Right",
    "ClubId": "22",
    "LeagueId": "19",
    "NationId": "10",
    "Rating": "77",
    "Attribute1": "78",
    "Attribute2": "76",
    "Attribute3": "76",
    "Attribute4": "76",
    "Attribute5": "65",
    "Attribute6": "80",
    "Rare": "0",
    "ItemType": "PlayerM"
  }
}