{
  "Player": {
    "FirstName": "Gerard",
    "LastName": "Doherty",
    "CommonName": null,
    "Height": "188",
    "DateOfBirth": {
      "Year": "1981",
      "Month": "8",
      "Day": "24"
    },
    "PreferredFoot": "Right",
    "ClubId": "445",
    "LeagueId": "65",
    "NationId": "25",
    "Rating": "57",
    "Attribute1": "60",
    "Attribute2": "55",
    "Attribute3": "57",
    "Attribute4": "59",
    "Attribute5": "33",
    "Attribute6": "57",
    "Rare": "0",
    "ItemType": "PlayerGk"
  }
}