{
  "Player": {
    "FirstName": "Giannis",
    "LastName": "Papadopoulos",
    "CommonName": null,
    "Height": "176",
    "DateOfBirth": {
      "Year": "1989",
      "Month": "3",
      "Day": "9"
    },
    "PreferredFoot": "Left",
    "ClubId": "503",
    "LeagueId": "20",
    "NationId": "22",
    "Rating": "69",
    "Attribute1": "76",
    "Attribute2": "66",
    "Attribute3": "69",
    "Attribute4": "64",
    "Attribute5": "68",
    "Attribute6": "51",
    "Rare": "0",
    "ItemType": "PlayerM"
  }
}