{
  "Player": {
    "FirstName": "Chris",
    "LastName": "Solly",
    "CommonName": null,
    "Height": "173",
    "DateOfBirth": {
      "Year": "1991",
      "Month": "1",
      "Day": "20"
    },
    "PreferredFoot": "Right",
    "ClubId": "89",
    "LeagueId": "60",
    "NationId": "14",
    "Rating": "59",
    "Attribute1": "69",
    "Attribute2": "36",
    "Attribute3": "62",
    "Attribute4": "55",
    "Attribute5": "61",
    "Attribute6": "61",
    "Rare": "0",
    "ItemType": "PlayerD"
  }
}