{
  "Player": {
    "FirstName": "Arkadiusz",
    "LastName": "Onyszko",
    "CommonName": null,
    "Height": "186",
    "DateOfBirth": {
      "Year": "1974",
      "Month": "1",
      "Day": "12"
    },
    "PreferredFoot": "Right",
    "ClubId": "1570",
    "LeagueId": "66",
    "NationId": "37",
    "Rating": "57",
    "Attribute1": "56",
    "Attribute2": "50",
    "Attribute3": "62",
    "Attribute4": "51",
    "Attribute5": "38",
    "Attribute6": "69",
    "Rare": "0",
    "ItemType": "PlayerGk"
  }
}