{
  "Player": {
    "FirstName": "Guillaume",
    "LastName": "Moullec",
    "CommonName": null,
    "Height": "175",
    "DateOfBirth": {
      "Year": "1980",
      "Month": "7",
      "Day": "30"
    },
    "PreferredFoot": "Right",
    "ClubId": "1815",
    "LeagueId": "17",
    "NationId": "18",
    "Rating": "59",
    "Attribute1": "60",
    "Attribute2": "46",
    "Attribute3": "63",
    "Attribute4": "60",
    "Attribute5": "60",
    "Attribute6": "63",
    "Rare": "0",
    "ItemType": "PlayerD"
  }
}