{
  "Player": {
    "FirstName": "Stephen",
    "LastName": "Warnock",
    "CommonName": null,
    "Height": "178",
    "DateOfBirth": {
      "Year": "1981",
      "Month": "12",
      "Day": "12"
    },
    "PreferredFoot": "Left",
    "ClubId": "2",
    "LeagueId": "13",
    "NationId": "14",
    "Rating": "75",
    "Attribute1": "68",
    "Attribute2": "46",
    "Attribute3": "67",
    "Attribute4": "62",
    "Attribute5": "75",
    "Attribute6": "70",
    "Rare": "0",
    "ItemType": "PlayerD"
  }
}