{
  "Player": {
    "FirstName": "Claudio",
    "LastName": "Terzi",
    "CommonName": null,
    "Height": "180",
    "DateOfBirth": {
      "Year": "1984",
      "Month": "6",
      "Day": "19"
    },
    "PreferredFoot": "Right",
    "ClubId": "1838",
    "LeagueId": "31",
    "NationId": "27",
    "Rating": "68",
    "Attribute1": "60",
    "Attribute2": "46",
    "Attribute3": "50",
    "Attribute4": "47",
    "Attribute5": "68",
    "Attribute6": "69",
    "Rare": "0",
    "ItemType": "PlayerD"
  }
}