{
  "Player": {
    "FirstName": "Jaime",
    "LastName": "Asensio Fuente",
    "CommonName": "Asen",
    "Height": "181",
    "DateOfBirth": {
      "Year": "1978",
      "Month": "10",
      "Day": "7"
    },
    "PreferredFoot": "Right",
    "ClubId": "571",
    "LeagueId": "54",
    "NationId": "45",
    "Rating": "63",
    "Attribute1": "60",
    "Attribute2": "63",
    "Attribute3": "48",
    "Attribute4": "58",
    "Attribute5": "45",
    "Attribute6": "66",
    "Rare": "1",
    "ItemType": "PlayerA"
  }
}