{
  "Player": {
    "FirstName": "Hasan",
    "LastName": "Kabze",
    "CommonName": null,
    "Height": "185",
    "DateOfBirth": {
      "Year": "1982",
      "Month": "5",
      "Day": "26"
    },
    "PreferredFoot": "Right",
    "ClubId": "70",
    "LeagueId": "16",
    "NationId": "48",
    "Rating": "71",
    "Attribute1": "62",
    "Attribute2": "73",
    "Attribute3": "68",
    "Attribute4": "74",
    "Attribute5": "52",
    "Attribute6": "66",
    "Rare": "1",
    "ItemType": "PlayerA"
  }
}