{
  "Player": {
    "FirstName": "Humberto",
    "LastName": "Suazo",
    "CommonName": null,
    "Height": "172",
    "DateOfBirth": {
      "Year": "1981",
      "Month": "5",
      "Day": "10"
    },
    "PreferredFoot": "Right",
    "ClubId": "1032",
    "LeagueId": "341",
    "NationId": "55",
    "Rating": "78",
    "Attribute1": "79",
    "Attribute2": "79",
    "Attribute3": "68",
    "Attribute4": "79",
    "Attribute5": "54",
    "Attribute6": "63",
    "Rare": "0",
    "ItemType": "PlayerA"
  }
}