{
  "Player": {
    "FirstName": "Chafik",
    "LastName": "Najih",
    "CommonName": null,
    "Height": "184",
    "DateOfBirth": {
      "Year": "1983",
      "Month": "8",
      "Day": "5"
    },
    "PreferredFoot": "Left",
    "ClubId": "111989",
    "LeagueId": "17",
    "NationId": "18",
    "Rating": "60",
    "Attribute1": "70",
    "Attribute2": "57",
    "Attribute3": "53",
    "Attribute4": "61",
    "Attribute5": "44",
    "Attribute6": "61",
    "Rare": "0",
    "ItemType": "PlayerM"
  }
}