{
  "Player": {
    "FirstName": "Harry",
    "LastName": "Pell",
    "CommonName": null,
    "Height": "188",
    "DateOfBirth": {
      "Year": "1991",
      "Month": "10",
      "Day": "21"
    },
    "PreferredFoot": "Right",
    "ClubId": "147",
    "LeagueId": "61",
    "NationId": "14",
    "Rating": "54",
    "Attribute1": "70",
    "Attribute2": "45",
    "Attribute3": "54",
    "Attribute4": "61",
    "Attribute5": "55",
    "Attribute6": "61",
    "Rare": "0",
    "ItemType": "PlayerM"
  }
}