{
  "Player": {
    "FirstName": "Julian",
    "LastName": "De Guzmán",
    "CommonName": null,
    "Height": "169",
    "DateOfBirth": {
      "Year": "1981",
      "Month": "3",
      "Day": "25"
    },
    "PreferredFoot": "Right",
    "ClubId": "111651",
    "LeagueId": "39",
    "NationId": "70",
    "Rating": "70",
    "Attribute1": "81",
    "Attribute2": "59",
    "Attribute3": "68",
    "Attribute4": "78",
    "Attribute5": "68",
    "Attribute6": "65",
    "Rare": "1",
    "ItemType": "PlayerM"
  }
}