{
  "Player": {
    "FirstName": "Peter",
    "LastName": "Crouch",
    "CommonName": null,
    "Height": "201",
    "DateOfBirth": {
      "Year": "1981",
      "Month": "1",
      "Day": "30"
    },
    "PreferredFoot": "Right",
    "ClubId": "1806",
    "LeagueId": "13",
    "NationId": "14",
    "Rating": "79",
    "Attribute1": "55",
    "Attribute2": "74",
    "Attribute3": "66",
    "Attribute4": "77",
    "Attribute5": "56",
    "Attribute6": "63",
    "Rare": "1",
    "ItemType": "PlayerA"
  }
}