{
  "Player": {
    "FirstName": "Eduard",
    "LastName": "Albácar Gallego",
    "CommonName": "Edu Albácar",
    "Height": "177",
    "DateOfBirth": {
      "Year": "1979",
      "Month": "11",
      "Day": "16"
    },
    "PreferredFoot": "Left",
    "ClubId": "468",
    "LeagueId": "54",
    "NationId": "45",
    "Rating": "68",
    "Attribute1": "74",
    "Attribute2": "65",
    "Attribute3": "68",
    "Attribute4": "65",
    "Attribute5": "67",
    "Attribute6": "63",
    "Rare": "0",
    "ItemType": "PlayerD"
  }
}