{
  "Player": {
    "FirstName": "Juan Jesús",
    "LastName": "Calatayud Sánchez",
    "CommonName": "Calatayud",
    "Height": "191",
    "DateOfBirth": {
      "Year": "1979",
      "Month": "12",
      "Day": "21"
    },
    "PreferredFoot": "Right",
    "ClubId": "453",
    "LeagueId": "53",
    "NationId": "45",
    "Rating": "74",
    "Attribute1": "76",
    "Attribute2": "71",
    "Attribute3": "64",
    "Attribute4": "80",
    "Attribute5": "56",
    "Attribute6": "74",
    "Rare": "1",
    "ItemType": "PlayerGk"
  }
}