{
  "Player": {
    "FirstName": "Leon",
    "LastName": "Andreasen",
    "CommonName": null,
    "Height": "185",
    "DateOfBirth": {
      "Year": "1983",
      "Month": "4",
      "Day": "23"
    },
    "PreferredFoot": "Right",
    "ClubId": "485",
    "LeagueId": "19",
    "NationId": "13",
    "Rating": "71",
    "Attribute1": "62",
    "Attribute2": "59",
    "Attribute3": "63",
    "Attribute4": "69",
    "Attribute5": "73",
    "Attribute6": "73",
    "Rare": "0",
    "ItemType": "PlayerM"
  }
}