{
  "Player": {
    "FirstName": "Ryan",
    "LastName": "Nelsen",
    "CommonName": null,
    "Height": "183",
    "DateOfBirth": {
      "Year": "1977",
      "Month": "10",
      "Day": "18"
    },
    "PreferredFoot": "Right",
    "ClubId": "3",
    "LeagueId": "13",
    "NationId": "198",
    "Rating": "77",
    "Attribute1": "46",
    "Attribute2": "37",
    "Attribute3": "48",
    "Attribute4": "40",
    "Attribute5": "80",
    "Attribute6": "85",
    "Rare": "1",
    "ItemType": "PlayerD"
  }
}