{
  "Player": {
    "FirstName": "Jemal",
    "LastName": "Johnson",
    "CommonName": null,
    "Height": "175",
    "DateOfBirth": {
      "Year": "1985",
      "Month": "5",
      "Day": "3"
    },
    "PreferredFoot": "Left",
    "ClubId": "1954",
    "LeagueId": "61",
    "NationId": "95",
    "Rating": "59",
    "Attribute1": "81",
    "Attribute2": "57",
    "Attribute3": "48",
    "Attribute4": "69",
    "Attribute5": "44",
    "Attribute6": "55",
    "Rare": "1",
    "ItemType": "PlayerM"
  }
}