{
  "Player": {
    "FirstName": "Javad",
    "LastName": "Nekounam",
    "CommonName": null,
    "Height": "186",
    "DateOfBirth": {
      "Year": "1980",
      "Month": "9",
      "Day": "7"
    },
    "PreferredFoot": "Right",
    "ClubId": "479",
    "LeagueId": "53",
    "NationId": "161",
    "Rating": "76",
    "Attribute1": "53",
    "Attribute2": "66",
    "Attribute3": "73",
    "Attribute4": "66",
    "Attribute5": "76",
    "Attribute6": "68",
    "Rare": "0",
    "ItemType": "PlayerM"
  }
}