{
  "Player": {
    "FirstName": "Kyel",
    "LastName": "Reid",
    "CommonName": null,
    "Height": "178",
    "DateOfBirth": {
      "Year": "1987",
      "Month": "11",
      "Day": "26"
    },
    "PreferredFoot": "Left",
    "ClubId": "1804",
    "LeagueId": "61",
    "NationId": "14",
    "Rating": "63",
    "Attribute1": "79",
    "Attribute2": "53",
    "Attribute3": "62",
    "Attribute4": "66",
    "Attribute5": "50",
    "Attribute6": "55",
    "Rare": "1",
    "ItemType": "PlayerM"
  }
}