{
  "Player": {
    "FirstName": "Nicklas",
    "LastName": "Pedersen",
    "CommonName": null,
    "Height": "187",
    "DateOfBirth": {
      "Year": "1987",
      "Month": "10",
      "Day": "21"
    },
    "PreferredFoot": "Right",
    "ClubId": "1915",
    "LeagueId": "10",
    "NationId": "13",
    "Rating": "67",
    "Attribute1": "64",
    "Attribute2": "65",
    "Attribute3": "46",
    "Attribute4": "64",
    "Attribute5": "53",
    "Attribute6": "66",
    "Rare": "0",
    "ItemType": "PlayerA"
  }
}