{
  "Player": {
    "FirstName": "Sascha",
    "LastName": "Dum",
    "CommonName": null,
    "Height": "189",
    "DateOfBirth": {
      "Year": "1986",
      "Month": "7",
      "Day": "3"
    },
    "PreferredFoot": "Left",
    "ClubId": "110636",
    "LeagueId": "20",
    "NationId": "21",
    "Rating": "64",
    "Attribute1": "87",
    "Attribute2": "58",
    "Attribute3": "59",
    "Attribute4": "68",
    "Attribute5": "57",
    "Attribute6": "52",
    "Rare": "1",
    "ItemType": "PlayerM"
  }
}