{
  "Player": {
    "FirstName": "Álvaro",
    "LastName": "González",
    "CommonName": null,
    "Height": "176",
    "DateOfBirth": {
      "Year": "1984",
      "Month": "10",
      "Day": "29"
    },
    "PreferredFoot": "Right",
    "ClubId": "46",
    "LeagueId": "31",
    "NationId": "60",
    "Rating": "74",
    "Attribute1": "77",
    "Attribute2": "66",
    "Attribute3": "76",
    "Attribute4": "72",
    "Attribute5": "71",
    "Attribute6": "64",
    "Rare": "1",
    "ItemType": "PlayerM"
  }
}