{
  "Player": {
    "FirstName": "José Julio",
    "LastName": "Gomes Gonçalves",
    "CommonName": "José Gonçalves",
    "Height": "188",
    "DateOfBirth": {
      "Year": "1985",
      "Month": "9",
      "Day": "17"
    },
    "PreferredFoot": "Left",
    "ClubId": "110770",
    "LeagueId": "189",
    "NationId": "38",
    "Rating": "63",
    "Attribute1": "65",
    "Attribute2": "47",
    "Attribute3": "58",
    "Attribute4": "56",
    "Attribute5": "69",
    "Attribute6": "71",
    "Rare": "0",
    "ItemType": "PlayerD"
  }
}