{
  "Player": {
    "FirstName": "Gavin",
    "LastName": "Gunning",
    "CommonName": null,
    "Height": "183",
    "DateOfBirth": {
      "Year": "1991",
      "Month": "1",
      "Day": "26"
    },
    "PreferredFoot": "Left",
    "ClubId": "181",
    "LeagueId": "50",
    "NationId": "25",
    "Rating": "65",
    "Attribute1": "60",
    "Attribute2": "47",
    "Attribute3": "56",
    "Attribute4": "37",
    "Attribute5": "67",
    "Attribute6": "73",
    "Rare": "0",
    "ItemType": "PlayerD"
  }
}