{
  "Player": {
    "FirstName": "Stephan",
    "LastName": "El Shaarawy",
    "CommonName": null,
    "Height": "178",
    "DateOfBirth": {
      "Year": "1992",
      "Month": "10",
      "Day": "27"
    },
    "PreferredFoot": "Right",
    "ClubId": "47",
    "LeagueId": "31",
    "NationId": "27",
    "Rating": "73",
    "Attribute1": "81",
    "Attribute2": "70",
    "Attribute3": "70",
    "Attribute4": "79",
    "Attribute5": "50",
    "Attribute6": "60",
    "Rare": "1",
    "ItemType": "PlayerM"
  }
}