{
  "Player": {
    "FirstName": "Matěj",
    "LastName": "Vydra",
    "CommonName": null,
    "Height": "180",
    "DateOfBirth": {
      "Year": "1992",
      "Month": "5",
      "Day": "1"
    },
    "PreferredFoot": "Right",
    "ClubId": "231",
    "LeagueId": "4",
    "NationId": "12",
    "Rating": "63",
    "Attribute1": "76",
    "Attribute2": "59",
    "Attribute3": "49",
    "Attribute4": "61",
    "Attribute5": "45",
    "Attribute6": "62",
    "Rare": "1",
    "ItemType": "PlayerA"
  }
}